CHANGES.txt
CONTRIBUTORS.txt
MANIFEST.in
README.txt
setup.py
docs/LICENSE.GPL
docs/LICENSE.txt
src/collective/__init__.py
src/collective.hootsuite.egg-info/PKG-INFO
src/collective.hootsuite.egg-info/SOURCES.txt
src/collective.hootsuite.egg-info/dependency_links.txt
src/collective.hootsuite.egg-info/entry_points.txt
src/collective.hootsuite.egg-info/namespace_packages.txt
src/collective.hootsuite.egg-info/not-zip-safe
src/collective.hootsuite.egg-info/requires.txt
src/collective.hootsuite.egg-info/top_level.txt
src/collective/hootsuite/__init__.py
src/collective/hootsuite/configure.zcml
src/collective/hootsuite/interfaces.py
src/collective/hootsuite/subscriber.py
src/collective/hootsuite/testing.py
src/collective/hootsuite/vocabulary.py
src/collective/hootsuite/browser/__init__.py
src/collective/hootsuite/browser/authorize.py
src/collective/hootsuite/browser/configure.zcml
src/collective/hootsuite/browser/controlpanel.py
src/collective/hootsuite/browser/controlpanel_layout.pt
src/collective/hootsuite/profiles/default/componentregistry.xml
src/collective/hootsuite/profiles/default/controlpanel.xml
src/collective/hootsuite/profiles/default/metadata.xml
src/collective/hootsuite/profiles/default/registry.xml
src/collective/hootsuite/tests/__init__.py
src/collective/hootsuite/tests/test_example.py