Metadata-Version: 1.0
Name: collective.hootsuite
Version: 1.1
Summary: Hootsuite Plone connector
Home-page: http://svn.plone.org/svn/collective/
Author: Ramon Navarro Bosch
Author-email: r.navarro@iskra.cat
License: gpl
Keywords: hootsuite plone
Platform: UNKNOWN
Classifier: Programming Language :: Python
